adminjournal/__init__.py
adminjournal/admin.py
adminjournal/apps.py
adminjournal/entry.py
adminjournal/mixins.py
adminjournal/models.py
adminjournal/monkeypatch.py
adminjournal/persistence.py
adminjournal/management/__init__.py
adminjournal/management/commands/__init__.py
adminjournal/management/commands/clearadminjournal.py
adminjournal/migrations/0001_initial.py
adminjournal/migrations/__init__.py
adminjournal/persistence_backends/__init__.py
adminjournal/persistence_backends/base.py
adminjournal/persistence_backends/db.py
adminjournal/persistence_backends/log.py
django_adminjournal-0.1.0.dist-info/LICENSE.rst
django_adminjournal-0.1.0.dist-info/METADATA
django_adminjournal-0.1.0.dist-info/WHEEL
django_adminjournal-0.1.0.dist-info/top_level.txt
django_adminjournal-0.1.0.dist-info/RECORD
