Metadata-Version: 2.1
Name: django-adminjournal
Version: 0.1.0
Summary: The library adds extended capabilities to log access to Django ModelAdmins.
Home-page: https://github.com/moccu/django-adminjournal
Author: Moccu GmbH & Co. KG
Author-email: info@moccu.com
License: UNKNOWN
Project-URL: Bug Reports, https://github.com/moccu/django-adminjournal/issues
Project-URL: Source, https://github.com/moccu/django-adminjournal
Keywords: django
Platform: UNKNOWN
Classifier: Environment :: Web Environment
Classifier: Framework :: Django
Classifier: Intended Audience :: Developers
Classifier: License :: OSI Approved :: MIT License
Classifier: Programming Language :: Python :: 3
Classifier: Programming Language :: Python :: 3.6
